product_datalab/__init__.py
product_datalab/orm.py
product_datalab-1.0.0.0.dist-info/METADATA
product_datalab-1.0.0.0.dist-info/WHEEL
product_datalab-1.0.0.0.dist-info/top_level.txt
product_datalab-1.0.0.0.dist-info/RECORD
