Metadata-Version: 2.1
Name: product-datalab
Version: 1.0.0.0
Summary: ORM with SQLAlchemy
Author: sonny_lee
Author-email: sonny_lee@gccompany.co.kr
License: MIT
Platform: UNKNOWN
Classifier: Programming Language :: Python :: 3
Classifier: Programming Language :: Python :: 3.2
Classifier: Programming Language :: Python :: 3.3
Classifier: Programming Language :: Python :: 3.4
Classifier: Programming Language :: Python :: 3.5
Classifier: Programming Language :: Python :: 3.6
Classifier: Programming Language :: Python :: 3.7
Classifier: Programming Language :: Python :: 3.8
Classifier: Programming Language :: Python :: 3.9
Classifier: Programming Language :: Python :: 3.10
Requires-Python: >=3
Requires-Dist: pandas
Requires-Dist: SQLAlchemy
Requires-Dist: sqlalchemy-redshift
Requires-Dist: psycopg2-binary
